{"obsYes": [{"reliable": false, "entries": [["n:-63:244"]]}, {"reliable": false, "entries": [["n:-90:128"]]}, {"reliable": false, "entries": [["n:-1:49"]]}, {"reliable": false, "entries": [["n:-63:197"]]}, {"reliable": false, "entries": [["n:-61:283"]]}, {"reliable": false, "entries": [["n:-24:35"]]}, {"reliable": false, "entries": [["n:-63:152"]]}, {"reliable": false, "entries": [["n:-90:182"]]}, {"reliable": false, "entries": [["n:-64:55"]]}, {"reliable": false, "entries": [["n:-15:273"]]}, {"reliable": false, "entries": [["n:-8:110"]]}, {"reliable": false, "entries": [["n:-28:23"]]}, {"reliable": false, "entries": [["n:-14:176"]]}, {"reliable": false, "entries": [["n:-42:154"]]}, {"reliable": false, "entries": [["n:-12:328"]]}, {"reliable": false, "entries": [["n:-12:130"]]}, {"reliable": false, "entries": [["n:-29:70"]]}, {"reliable": false, "entries": [["n:-27:162"]]}, {"reliable": false, "entries": [["n:-58:89"]]}, {"reliable": false, "entries": [["n:-90:157"]]}, {"reliable": false, "entries": [["n:-4:25"]]}, {"reliable": false, "entries": [["n:-62:24"]]}, {"reliable": false, "entries": [["n:-90:194"]]}, {"reliable": false, "entries": [["n:-27:189"]]}, {"reliable": false, "entries": [["n:-27:183"]]}, {"reliable": false, "entries": [["n:-14:196"]]}, {"reliable": false, "entries": [["n:-1:33"]]}, {"reliable": false, "entries": [["n:-63:217"]]}, {"reliable": false, "entries": [["n:-12:250"]]}, {"reliable": false, "entries": [["n:-61:298"]]}, {"reliable": false, "entries": [["n:-15:873"]]}, {"reliable": false, "entries": [["n:-61:172"]]}, {"reliable": false, "entries": [["n:-63:104"]]}, {"reliable": false, "entries": [["n:-68:35"]]}, {"reliable": false, "entries": [["n:-12:164"]]}, {"reliable": false, "entries": [["n:-12:298"]]}, {"reliable": false, "entries": [["n:-57:277"]]}, {"reliable": false, "entries": [["n:-10:141"]]}, {"reliable": false, "entries": [["n:-27:175"]]}, {"reliable": false, "entries": [["n:-12:311"]]}, {"reliable": false, "entries": [["n:-64:65"]]}, {"reliable": false, "entries": [["n:-57:292"]]}, {"reliable": false, "entries": [["n:-27:135"]]}, {"reliable": false, "entries": [["n:-26:612"]]}, {"reliable": false, "entries": [["n:-15:375"]]}, {"reliable": false, "entries": [["n:-90:168"]]}, {"reliable": false, "entries": [["n:-14:202"]]}], "crash": ["n:-88:64"], "stack": [{"entry": ["n:-42:1"], "call": ["n:-27:352"]}, {"entry": ["n:-88:1"], "call": ["n:-42:200"]}], "obsNo": [["n:-27:315"], ["n:-73:283"], ["n:-54:663"], ["n:-65:538"], ["n:-14:70"], ["n:-26:218"], ["n:-7:197"], ["n:-53:97"], ["n:-102:109"], ["n:-115:74"], ["n:-67:28"], ["n:-6:106"], ["n:-15:633"], ["n:-106:51"], ["n:-54:644"], ["n:-41:378"], ["n:-26:278"], ["n:-115:88"], ["n:-29:109"], ["n:-54:251"], ["n:-102:124"], ["n:-100:677"], ["n:-100:670"], ["n:-41:399"], ["n:-15:969"], ["n:-41:356"], ["n:-100:427"], ["n:-26:528"], ["n:-7:157"], ["n:-34:22"], ["n:-102:147"], ["n:-100:280"], ["n:-15:907"], ["n:-54:354"], ["n:-41:336"], ["n:-12:268"], ["n:-15:747"], ["n:-15:742"], ["n:-103:135"], ["n:-29:97"], ["n:-95:97"], ["n:-7:175"], ["n:-3:80"], ["n:-73:522"], ["n:-102:166"], ["n:-96:72"], ["n:-121:46"], ["n:-27:285"], ["n:-97:74"], ["n:-49:300"], ["n:-103:111"], ["n:-100:201"], ["n:-26:296"], ["n:-73:329"], ["n:-7:111"], ["n:-98:49"], ["n:-49:511"], ["n:-96:52"], ["n:-26:177"], ["n:-96:133"], ["n:-15:700"], ["n:-15:706"], ["n:-56:39"], ["n:-41:196"], ["n:-26:546"], ["n:-51:26"], ["n:-14:138"], ["n:-73:304"], ["n:-73:308"], ["n:-54:695"], ["n:-45:435"], ["n:-70:183"], ["n:-26:156"], ["n:-14:120"], ["n:-98:119"], ["n:-100:291"], ["n:-14:113"], ["n:-12:235"], ["n:-73:589"], ["n:-82:31"], ["n:-26:131"], ["n:-69:220"], ["n:-69:228"], ["n:-27:264"], ["n:-26:588"], ["n:-8:131"], ["n:-70:145"], ["n:-35:28"], ["n:-100:500"], ["n:-65:198"], ["n:-73:424"], ["n:-41:283"], ["n:-65:463"], ["n:-102:137"], ["n:-6:88"], ["n:-82:24"], ["n:-25:35"], ["n:-100:267"], ["n:-26:468"], ["n:-27:227"], ["n:-100:662"], ["n:-42:174"], ["n:-69:65"], ["n:-68:45"], ["n:-54:532"], ["n:-102:63"], ["n:-26:322"], ["n:-39:19"], ["n:-70:103"], ["n:-54:704"], ["n:-29:131"], ["n:-15:572"], ["n:-52:122"], ["n:-26:408"], ["n:-86:33"], ["n:-42:190"], ["n:-79:35"], ["n:-73:173"], ["n:-73:179"], ["n:-41:247"], ["n:-100:686"], ["n:-26:340"], ["n:-70:123"], ["n:-98:64"], ["n:-35:43"], ["n:-70:95"], ["n:-103:91"], ["n:-26:426"], ["n:-100:715"], ["n:-42:202"], ["n:-42:208"], ["n:-41:267"], ["n:-41:263"], ["n:-53:133"], ["n:-40:37"], ["n:-70:72"], ["n:-103:72"], ["n:-95:48"], ["n:-72:110"], ["n:-102:82"], ["n:-36:22"], ["n:-106:81"], ["n:-29:153"], ["n:-26:606"], ["n:-95:60"], ["n:-95:66"], ["n:-73:299"], ["n:-115:117"], ["n:-41:141"], ["n:-41:411"], ["n:-26:486"], ["n:-54:593"], ["n:-49:622"], ["n:-100:608"], ["n:-115:63"], ["n:-121:39"], ["n:-49:377"], ["n:-49:443"], ["n:-100:646"], ["n:-106:123"], ["n:-15:302"], ["n:-42:79"], ["n:-31:23"], ["n:-31:29"], ["n:-67:33"], ["n:-67:37"], ["n:-54:687"], ["n:-15:391"], ["n:-54:469"], ["n:-100:479"], ["n:-52:82"], ["n:-41:366"], ["n:-100:411"], ["n:-106:159"], ["n:-35:37"], ["n:-73:579"], ["n:-27:359"], ["n:-42:94"], ["n:-55:102"], ["n:-15:584"], ["n:-41:348"], ["n:-41:343"], ["n:-41:388"], ["n:-41:126"], ["n:-56:69"], ["n:-88:54"], ["n:-106:178"], ["n:-73:515"], ["n:-73:510"], ["n:-34:36"], ["n:-108:29"], ["n:-100:465"], ["n:-96:64"], ["n:-15:917"], ["n:-29:183"], ["n:-41:326"], ["n:-38:19"], ["n:-15:757"], ["n:-100:238"], ["n:-106:115"], ["n:-3:96"], ["n:-7:94"], ["n:-55:149"], ["n:-55:142"], ["n:-52:199"], ["n:-100:578"], ["n:-27:297"], ["n:-100:249"], ["n:-54:363"], ["n:-41:304"], ["n:-65:280"], ["n:-100:216"], ["n:-51:34"], ["n:-106:137"], ["n:-108:60"], ["n:-100:550"], ["n:-26:144"], ["n:-97:49"], ["n:-54:169"], ["n:-54:303"], ["n:-100:725"], ["n:-45:446"], ["n:-78:19"], ["n:-7:50"], ["n:-65:177"], ["n:-23:27"], ["n:-100:531"], ["n:-27:257"], ["n:-98:109"], ["n:-100:222"], ["n:-42:128"], ["n:-69:99"], ["n:-88:66"], ["n:-15:852"], ["n:-65:159"], ["n:-100:517"], ["n:-69:235"], ["n:-27:277"], ["n:-50:40"], ["n:-9:21"], ["n:-27:349"], ["n:-42:140"], ["n:-65:454"], ["n:-106:169"], ["n:-14:163"], ["n:-100:182"], ["n:-15:835"], ["n:-100:389"], ["n:-95:117"], ["n:-27:214"], ["n:-50:61"], ["n:-41:296"], ["n:-100:308"], ["n:-15:814"], ["n:-106:96"], ["n:-54:712"], ["n:-65:605"], ["n:-103:101"], ["n:-27:233"], ["n:-42:148"], ["n:-73:166"], ["n:-73:261"], ["n:-65:273"], ["n:-29:145"], ["n:-55:135"], ["n:-100:329"], ["n:-26:334"], ["n:-8:56"], ["n:-60:96"], ["n:-41:152"], ["n:-96:126"], ["n:-41:255"], ["n:-53:124"], ["n:-72:143"], ["n:-100:694"], ["n:-15:628"], ["n:-100:347"], ["n:-26:355"], ["n:-52:170"], ["n:-49:163"], ["n:-49:322"], ["n:-98:88"], ["n:-98:82"], ["n:-103:125"], ["n:-100:592"], ["n:-72:128"], ["n:-100:368"], ["n:-27:354"], ["n:-106:68"], ["n:-96:113"], ["n:-29:167"], ["n:-41:169"], ["n:-69:166"], ["n:-95:77"], ["n:-41:213"], ["n:-41:210"], ["n:-49:229"], ["n:-100:624"], ["n:-102:94"], ["n:-36:34"], ["n:-54:399"], ["n:-6:72"], ["n:-41:404"], ["n:-100:448"], ["n:-26:236"], ["n:-54:210"], ["n:-55:61"], ["n:-41:235"], ["n:-97:64"], ["n:-121:27"], ["n:-53:141"], ["n:-15:680"], ["n:-47:38"]]}